improveai/__init__.py
improveai/decision.py
improveai/decision_context.py
improveai/decision_model.py
improveai/decision_tracker.py
improveai/feature_encoder.py
improveai/givens_provider.py
improveai/improve_model_cli.py
improveai/settings.py
improveai/choosers/__init__.py
improveai/choosers/basic_choosers.py
improveai/choosers/mlmodel_chooser.py
improveai/choosers/xgb_chooser.py
improveai/cythonized_feature_encoding/__init__.py
improveai/cythonized_feature_encoding/__init__.pyx
improveai/cythonized_feature_encoding/cythonized_feature_encoder.cpython-38-darwin.so
improveai/cythonized_feature_encoding/cythonized_feature_encoder.pyx
improveai/cythonized_feature_encoding/cythonized_feature_encoding_utils.cpython-38-darwin.so
improveai/cythonized_feature_encoding/cythonized_feature_encoding_utils.pyx
improveai/cythonized_feature_encoding/npy_no_deprecated_api.h
improveai/utils/__init__.py
improveai/utils/choosers_feature_encoding_tools.py
improveai/utils/general_purpose_tools.py
improveai/utils/gzip_tools.py
improveai/utils/url_tools.py
improveai-7.0.1.dist-info/LICENSE
improveai-7.0.1.dist-info/METADATA
improveai-7.0.1.dist-info/WHEEL
improveai-7.0.1.dist-info/top_level.txt
improveai-7.0.1.dist-info/RECORD
