Metadata-Version: 2.1
Name: improveai
Version: 7.0.1
Summary: Improve AI: AI Decisions for iOS, Android, and the Cloud
Home-page: https://github.com/improve-ai/python-sdk
Author: Justin Chapweske
Author-email: support@improve.ai
License: UNKNOWN
Platform: UNKNOWN
License-File: LICENSE
Requires-Dist: setuptools
Requires-Dist: wheel
Requires-Dist: Cython (>=0.29.14)
Requires-Dist: xxhash (==2.0.0)
Requires-Dist: coremltools (==4.1)
Requires-Dist: requests (>=2.24.0)
Requires-Dist: numpy (>=1.19.2)
Requires-Dist: xgboost (==1.4.2)
Requires-Dist: simplejson (==3.17.2)
Requires-Dist: orjson
Requires-Dist: svix-ksuid
